clean_auckland_gtfs/__init__.py
clean_auckland_gtfs/main.py
clean_auckland_gtfs-0.5.0.dist-info/LICENSE
clean_auckland_gtfs-0.5.0.dist-info/WHEEL
clean_auckland_gtfs-0.5.0.dist-info/METADATA
clean_auckland_gtfs-0.5.0.dist-info/RECORD
